selenium_support-0.0.1-py3.8-nspkg.pth
alexber/seleniumsupport/__init__.py
alexber/seleniumsupport/_impl.py
alexber/seleniumsupport/data/__init__.py
tests_data/__init__.py
tests_data/tests/__init__.py
selenium_support-0.0.1.dist-info/LICENSE.txt
selenium_support-0.0.1.dist-info/METADATA
selenium_support-0.0.1.dist-info/WHEEL
selenium_support-0.0.1.dist-info/namespace_packages.txt
selenium_support-0.0.1.dist-info/top_level.txt
selenium_support-0.0.1.dist-info/RECORD
